{
  "schemaVersion": 1,
  "lastUpdated": "2026-07-01",
  "purpose": "Track final App Store screenshot evidence. Set captured/reviewed values to true only after the matching final native/TestFlight or native simulator screenshot evidence exists.",
  "iphone69": {
    "captured": true,
    "source": "Native iOS simulator Debug build",
    "capturedAt": "2026-07-01T06:38:01Z",
    "device": "iPhone 17 Pro Max simulator, iOS 26.5",
    "appBuild": "UCLA Sports MRI 1.0 (1), Debug iphonesimulator",
    "files": [
      "iphone-6-9-01-dashboard.png",
      "iphone-6-9-02-normal-guided-tour.png",
      "iphone-6-9-03-knowledge-check.png",
      "iphone-6-9-04-cross-plane.png",
      "iphone-6-9-05-cases.png",
      "iphone-6-9-06-spaced-review.png",
      "iphone-6-9-07-progress.png"
    ]
  },
  "ipad13": {
    "captured": true,
    "source": "Native iOS simulator Debug build",
    "capturedAt": "2026-07-01T06:38:01Z",
    "device": "iPad Pro 13-inch (M5) simulator, iOS 26.5",
    "appBuild": "UCLA Sports MRI 1.0 (1), Debug iphonesimulator",
    "files": [
      "ipad-13-01-dashboard.png",
      "ipad-13-02-normal-guided-tour.png",
      "ipad-13-03-knowledge-check.png",
      "ipad-13-04-cross-plane.png",
      "ipad-13-05-cases.png",
      "ipad-13-06-spaced-review.png",
      "ipad-13-07-progress.png"
    ]
  },
  "phiReview": {
    "reviewed": true,
    "noPhiConfirmed": true,
    "reviewedAt": "2026-07-01T06:38:01Z",
    "reviewer": "Codex visual review",
    "notes": "Reviewed all fourteen generated App Store screenshots via contact sheet and spot checks. No PHI, real learner identity, localhost/browser chrome, login screen, simulator notification banner, or debug overlay visible. MRI image areas are visible on screenshots 02-04."
  }
}
